{
  "palavras": [
    {
      "palavra": "ANA"
    },
    {
      "palavra": "HTML"
    },
    {
      "palavra": "CANOAS"
    },
    {
      "palavra": "COMPUTADOR"
    },
    {
      "palavra": "PLAYSTATION"
    },
    {
      "palavra": "TELEVISAO"
    },
    {
      "palavra": "BROWSER"
    },
    {
      "palavra": "BOLO"
    },
    {
      "palavra": "MOCHILA"
    },
    {
      "palavra": "SHIMBALAIE"
    },
    {
      "palavra": "INCONSTITUCIONAL"
    },
    {
      "palavra": "INCORRUPTIVEL"
    },
    {
      "palavra": "EXPERIMENTAÇAO"
    },
    {
      "palavra": "JAR JAR BINKS"
    },
    {
      "palavra": "LATIFUNDIARIO"
    },
    {
      "palavra": "REENCARNAÇAO"
    },
    {
      "palavra": "SENSACIONALISMO"
    },
    {
      "palavra": "QUERO IBAGENS"
    },
    {
      "palavra": "MOCHILA"
    }
  ],
  "pessoas": [
    {
      "nome": "ASTROGILDO",
      "pontos": 0
    },
    {
      "nome": "JOAO",
      "pontos": 0
    },
    {
      "nome": "JUCA",
      "pontos": 0
    }
  ]
}
